{
  "type": "FeatureCollection",
  "features": [
    {
      "type": "Feature",
      "geometry": {
        "type": "Point",
        "coordinates": [
          -64.6208,
          18.4167
        ]
      },
      "properties": {
        "controller_id": "https://chompchomp.example",
        "controller_name": "chompchomp",
        "fraud_type": null
      }
    },
    {
      "type": "Feature",
      "geometry": {
        "type": "Point",
        "coordinates": [
          -68.0125,
          10.4647
        ]
      },
      "properties": {
        "controller_id": "https://camaron-corriente.example",
        "controller_name": "camaron-corriente",
        "fraud_type": null
      }
    },
    {
      "type": "Feature",
      "geometry": {
        "type": "Point",
        "coordinates": [
          -61.5167,
          10.6596
        ]
      },
      "properties": {
        "controller_id": "https://legit-shrimp.example",
        "controller_name": "legit-shrimp",
        "fraud_type": null
      }
    },
    {
      "type": "Feature",
      "geometry": {
        "type": "Point",
        "coordinates": [
          -70.027,
          12.5186
        ]
      },
      "properties": {
        "controller_id": "https://shady-carrier.example",
        "controller_name": "shady-carrier",
        "fraud_type": null
      }
    },
    {
      "type": "Feature",
      "geometry": {
        "type": "Point",
        "coordinates": [
          -64.6208,
          18.4167
        ]
      },
      "properties": {
        "controller_id": "https://shady-distributor.example",
        "controller_name": "shady-distributor",
        "fraud_type": null
      }
    },
    {
      "type": "Feature",
      "geometry": {
        "type": "Point",
        "coordinates": [
          -66.1057,
          18.4655
        ]
      },
      "properties": {
        "controller_id": "https://cargo-line.example",
        "controller_name": "cargo-line",
        "fraud_type": null
      }
    },
    {
      "type": "Feature",
      "geometry": {
        "type": "Point",
        "coordinates": [
          -64.9307,
          18.3419
        ]
      },
      "properties": {
        "controller_id": "https://anonymous-distributor.example",
        "controller_name": "anonymous-distributor",
        "fraud_type": null
      }
    },
    {
      "type": "Feature",
      "geometry": {
        "type": "Point",
        "coordinates": [
          -80.1918,
          25.7617
        ]
      },
      "properties": {
        "controller_id": "https://honest-importer.example",
        "controller_name": "honest-importer",
        "fraud_type": null
      }
    }
  ]
}